<esri:Workspace xmlns:esri='http://www.esri.com/schemas/ArcGIS/10.1' xmlns:xsi='http://www.w3.org/2001/XMLSchema-instance' xmlns:xs='http://www.w3.org/2001/XMLSchema'><WorkspaceDefinition xsi:type='esri:WorkspaceDefinition'><WorkspaceType>esriLocalDatabaseWorkspace</WorkspaceType><Version></Version><Domains xsi:type='esri:ArrayOfDomain'><Domain xsi:type='esri:CodedValueDomain'><DomainName>ServiceClass</DomainName><FieldType>esriFieldTypeSmallInteger</FieldType><MergePolicy>esriMPTDefaultValue</MergePolicy><SplitPolicy>esriSPTDefaultValue</SplitPolicy><Description>ServiceClass</Description><Owner></Owner><CodedValues xsi:type='esri:ArrayOfCodedValue'><CodedValue xsi:type='esri:CodedValue'><Name>Service within 1 month</Name><Code xsi:type='xs:short'>1</Code></CodedValue><CodedValue xsi:type='esri:CodedValue'><Name>Service within 9 months</Name><Code xsi:type='xs:short'>9</Code></CodedValue></CodedValues></Domain><Domain xsi:type='esri:CodedValueDomain'><DomainName>AreaCode</DomainName><FieldType>esriFieldTypeSmallInteger</FieldType><MergePolicy>esriMPTDefaultValue</MergePolicy><SplitPolicy>esriSPTDefaultValue</SplitPolicy><Description>AreaCode</Description><Owner></Owner><CodedValues xsi:type='esri:ArrayOfCodedValue'><CodedValue xsi:type='esri:CodedValue'><Name>Developed Area</Name><Code xsi:type='xs:short'>1</Code></CodedValue><CodedValue xsi:type='esri:CodedValue'><Name>Transport Corridor</Name><Code xsi:type='xs:short'>2</Code></CodedValue><CodedValue xsi:type='esri:CodedValue'><Name>Other</Name><Code xsi:type='xs:short'>3</Code></CodedValue></CodedValues></Domain></Domains><DatasetDefinitions xsi:type='esri:ArrayOfDataElement'><DataElement xsi:type='esri:DEFeatureClass'><CatalogPath>/FC=Hexagons</CatalogPath><Name>Hexagons</Name><MetadataRetrieved>true</MetadataRetrieved><Metadata xsi:type='esri:XmlPropertySet'><XmlDoc>&lt;metadata xml:lang=&quot;en&quot;&gt;&lt;Esri&gt;&lt;CreaDate&gt;20140617&lt;/CreaDate&gt;&lt;CreaTime&gt;15001600&lt;/CreaTime&gt;&lt;ArcGISFormat&gt;1.0&lt;/ArcGISFormat&gt;&lt;SyncOnce&gt;TRUE&lt;/SyncOnce&gt;&lt;DataProperties&gt;&lt;lineage&gt;&lt;Process ToolSource=&quot;c:\program files\arcgis\desktop10.1\ArcToolbox\Toolboxes\Data Management Tools.tbx\CalculateField&quot; Date=&quot;20140617&quot; Time=&quot;150016&quot;&gt;CalculateField Hexagons AreaCode &quot;1&quot; VB #&lt;/Process&gt;&lt;Process ToolSource=&quot;c:\program files\arcgis\desktop10.1\ArcToolbox\Toolboxes\Data Management Tools.tbx\AssignDomainToField&quot; Date=&quot;20140617&quot; Time=&quot;164952&quot;&gt;AssignDomainToField Hexagons AreaCode AreaCode #&lt;/Process&gt;&lt;Process ToolSource=&quot;c:\program files\arcgis\desktop10.1\ArcToolbox\Toolboxes\Data Management Tools.tbx\CalculateField&quot; Date=&quot;20140618&quot; Time=&quot;142531&quot;&gt;CalculateField Hexagons AreaCode &quot;3&quot; VB #&lt;/Process&gt;&lt;/lineage&gt;&lt;/DataProperties&gt;&lt;/Esri&gt;&lt;/metadata&gt;
</XmlDoc></Metadata><DatasetType>esriDTFeatureClass</DatasetType><DSID>4</DSID><Versioned>false</Versioned><CanVersion>false</CanVersion><ConfigurationKeyword></ConfigurationKeyword><HasOID>true</HasOID><OIDFieldName>OBJECTID</OIDFieldName><Fields xsi:type='esri:Fields'><FieldArray xsi:type='esri:ArrayOfField'><Field xsi:type='esri:Field'><Name>OBJECTID</Name><Type>esriFieldTypeOID</Type><IsNullable>false</IsNullable><Length>4</Length><Precision>0</Precision><Scale>0</Scale><Required>true</Required><Editable>false</Editable><DomainFixed>true</DomainFixed><AliasName>OBJECTID</AliasName><ModelName>OBJECTID</ModelName></Field><Field xsi:type='esri:Field'><Name>SHAPE</Name><Type>esriFieldTypeGeometry</Type><IsNullable>true</IsNullable><Length>0</Length><Precision>0</Precision><Scale>0</Scale><Required>true</Required><DomainFixed>true</DomainFixed><GeometryDef xsi:type='esri:GeometryDef'><AvgNumPoints>0</AvgNumPoints><GeometryType>esriGeometryPolygon</GeometryType><HasM>false</HasM><HasZ>false</HasZ><SpatialReference xsi:type='esri:ProjectedCoordinateSystem'><WKT>PROJCS[&quot;NAD_1983_UTM_Zone_12N&quot;,GEOGCS[&quot;GCS_North_American_1983&quot;,DATUM[&quot;D_North_American_1983&quot;,SPHEROID[&quot;GRS_1980&quot;,6378137.0,298.257222101]],PRIMEM[&quot;Greenwich&quot;,0.0],UNIT[&quot;Degree&quot;,0.0174532925199433]],PROJECTION[&quot;Transverse_Mercator&quot;],PARAMETER[&quot;False_Easting&quot;,500000.0],PARAMETER[&quot;False_Northing&quot;,0.0],PARAMETER[&quot;Central_Meridian&quot;,-111.0],PARAMETER[&quot;Scale_Factor&quot;,0.9996],PARAMETER[&quot;Latitude_Of_Origin&quot;,0.0],UNIT[&quot;Meter&quot;,1.0],AUTHORITY[&quot;EPSG&quot;,26912]]</WKT><XOrigin>-5120900</XOrigin><YOrigin>-9998100</YOrigin><XYScale>100</XYScale><ZOrigin>0</ZOrigin><ZScale>1</ZScale><MOrigin>0</MOrigin><MScale>1</MScale><XYTolerance>0.10000000000000001</XYTolerance><ZTolerance>0.001</ZTolerance><MTolerance>0.001</MTolerance><HighPrecision>true</HighPrecision><WKID>26912</WKID><LatestWKID>26912</LatestWKID></SpatialReference><GridSize0>1000</GridSize0></GeometryDef><AliasName>SHAPE</AliasName><ModelName>SHAPE</ModelName></Field><Field xsi:type='esri:Field'><Name>SHAPE_Length</Name><Type>esriFieldTypeDouble</Type><IsNullable>true</IsNullable><Length>8</Length><Precision>0</Precision><Scale>0</Scale><Required>true</Required><Editable>false</Editable><AliasName>SHAPE_Length</AliasName><ModelName>SHAPE_Length</ModelName></Field><Field xsi:type='esri:Field'><Name>SHAPE_Area</Name><Type>esriFieldTypeDouble</Type><IsNullable>true</IsNullable><Length>8</Length><Precision>0</Precision><Scale>0</Scale><Required>true</Required><Editable>false</Editable><AliasName>SHAPE_Area</AliasName><ModelName>SHAPE_Area</ModelName></Field><Field xsi:type='esri:Field'><Name>AreaCode</Name><Type>esriFieldTypeSmallInteger</Type><IsNullable>true</IsNullable><Length>2</Length><Precision>0</Precision><Scale>0</Scale><AliasName>AreaCode</AliasName><ModelName>AreaCode</ModelName><Domain xsi:type='esri:CodedValueDomain'><DomainName>AreaCode</DomainName><FieldType>esriFieldTypeSmallInteger</FieldType><MergePolicy>esriMPTDefaultValue</MergePolicy><SplitPolicy>esriSPTDefaultValue</SplitPolicy><Description>AreaCode</Description><Owner></Owner><CodedValues xsi:type='esri:ArrayOfCodedValue'><CodedValue xsi:type='esri:CodedValue'><Name>Developed Area</Name><Code xsi:type='xs:short'>1</Code></CodedValue><CodedValue xsi:type='esri:CodedValue'><Name>Transport Corridor</Name><Code xsi:type='xs:short'>2</Code></CodedValue><CodedValue xsi:type='esri:CodedValue'><Name>Other</Name><Code xsi:type='xs:short'>3</Code></CodedValue></CodedValues></Domain></Field><Field xsi:type='esri:Field'><Name>HexID</Name><Type>esriFieldTypeInteger</Type><IsNullable>true</IsNullable><Length>4</Length><Precision>0</Precision><Scale>0</Scale><AliasName>HexID</AliasName><ModelName>HexID</ModelName></Field></FieldArray></Fields><Indexes xsi:type='esri:Indexes'><IndexArray xsi:type='esri:ArrayOfIndex'><Index xsi:type='esri:Index'><Name>FDO_OBJECTID</Name><IsUnique>true</IsUnique><IsAscending>true</IsAscending><Fields xsi:type='esri:Fields'><FieldArray xsi:type='esri:ArrayOfField'><Field xsi:type='esri:Field'><Name>OBJECTID</Name><Type>esriFieldTypeOID</Type><IsNullable>false</IsNullable><Length>4</Length><Precision>0</Precision><Scale>0</Scale><Required>true</Required><Editable>false</Editable><DomainFixed>true</DomainFixed><AliasName>OBJECTID</AliasName><ModelName>OBJECTID</ModelName></Field></FieldArray></Fields></Index><Index xsi:type='esri:Index'><Name>FDO_SHAPE</Name><IsUnique>false</IsUnique><IsAscending>true</IsAscending><Fields xsi:type='esri:Fields'><FieldArray xsi:type='esri:ArrayOfField'><Field xsi:type='esri:Field'><Name>SHAPE</Name><Type>esriFieldTypeGeometry</Type><IsNullable>true</IsNullable><Length>0</Length><Precision>0</Precision><Scale>0</Scale><Required>true</Required><DomainFixed>true</DomainFixed><GeometryDef xsi:type='esri:GeometryDef'><AvgNumPoints>0</AvgNumPoints><GeometryType>esriGeometryPolygon</GeometryType><HasM>false</HasM><HasZ>false</HasZ><SpatialReference xsi:type='esri:ProjectedCoordinateSystem'><WKT>PROJCS[&quot;NAD_1983_UTM_Zone_12N&quot;,GEOGCS[&quot;GCS_North_American_1983&quot;,DATUM[&quot;D_North_American_1983&quot;,SPHEROID[&quot;GRS_1980&quot;,6378137.0,298.257222101]],PRIMEM[&quot;Greenwich&quot;,0.0],UNIT[&quot;Degree&quot;,0.0174532925199433]],PROJECTION[&quot;Transverse_Mercator&quot;],PARAMETER[&quot;False_Easting&quot;,500000.0],PARAMETER[&quot;False_Northing&quot;,0.0],PARAMETER[&quot;Central_Meridian&quot;,-111.0],PARAMETER[&quot;Scale_Factor&quot;,0.9996],PARAMETER[&quot;Latitude_Of_Origin&quot;,0.0],UNIT[&quot;Meter&quot;,1.0],AUTHORITY[&quot;EPSG&quot;,26912]]</WKT><XOrigin>-5120900</XOrigin><YOrigin>-9998100</YOrigin><XYScale>100</XYScale><ZOrigin>0</ZOrigin><ZScale>1</ZScale><MOrigin>0</MOrigin><MScale>1</MScale><XYTolerance>0.10000000000000001</XYTolerance><ZTolerance>0.001</ZTolerance><MTolerance>0.001</MTolerance><HighPrecision>true</HighPrecision><WKID>26912</WKID><LatestWKID>26912</LatestWKID></SpatialReference><GridSize0>1000</GridSize0></GeometryDef><AliasName>SHAPE</AliasName><ModelName>SHAPE</ModelName></Field></FieldArray></Fields></Index><Index xsi:type='esri:Index'><Name>GDB_4_HexID</Name><IsUnique>false</IsUnique><IsAscending>true</IsAscending><Fields xsi:type='esri:Fields'><FieldArray xsi:type='esri:ArrayOfField'><Field xsi:type='esri:Field'><Name>HexID</Name><Type>esriFieldTypeInteger</Type><IsNullable>true</IsNullable><Length>4</Length><Precision>0</Precision><Scale>0</Scale><AliasName>HexID</AliasName><ModelName>HexID</ModelName></Field></FieldArray></Fields></Index></IndexArray></Indexes><CLSID>{52353152-891A-11D0-BEC6-00805F7C4268}</CLSID><EXTCLSID></EXTCLSID><RelationshipClassNames xsi:type='esri:Names'><Name>HexagontoPSAs</Name></RelationshipClassNames><AliasName>Hexagons</AliasName><ModelName></ModelName><HasGlobalID>false</HasGlobalID><GlobalIDFieldName></GlobalIDFieldName><RasterFieldName></RasterFieldName><ExtensionProperties xsi:type='esri:PropertySet'><PropertyArray xsi:type='esri:ArrayOfPropertySetProperty'></PropertyArray></ExtensionProperties><ControllerMemberships xsi:type='esri:ArrayOfControllerMembership'></ControllerMemberships><EditorTrackingEnabled>false</EditorTrackingEnabled><CreatorFieldName></CreatorFieldName><CreatedAtFieldName></CreatedAtFieldName><EditorFieldName></EditorFieldName><EditedAtFieldName></EditedAtFieldName><IsTimeInUTC>true</IsTimeInUTC><FeatureType>esriFTSimple</FeatureType><ShapeType>esriGeometryPolygon</ShapeType><ShapeFieldName>SHAPE</ShapeFieldName><HasM>false</HasM><HasZ>false</HasZ><HasSpatialIndex>true</HasSpatialIndex><AreaFieldName>SHAPE_Area</AreaFieldName><LengthFieldName>SHAPE_Length</LengthFieldName><Extent xsi:type='esri:EnvelopeN'><XMin>227708.4299999997</XMin><YMin>4094310.8900000006</YMin><XMax>674208.4299999997</XMax><YMax>4654196.3100000005</YMax><SpatialReference xsi:type='esri:ProjectedCoordinateSystem'><WKT>PROJCS[&quot;NAD_1983_UTM_Zone_12N&quot;,GEOGCS[&quot;GCS_North_American_1983&quot;,DATUM[&quot;D_North_American_1983&quot;,SPHEROID[&quot;GRS_1980&quot;,6378137.0,298.257222101]],PRIMEM[&quot;Greenwich&quot;,0.0],UNIT[&quot;Degree&quot;,0.0174532925199433]],PROJECTION[&quot;Transverse_Mercator&quot;],PARAMETER[&quot;False_Easting&quot;,500000.0],PARAMETER[&quot;False_Northing&quot;,0.0],PARAMETER[&quot;Central_Meridian&quot;,-111.0],PARAMETER[&quot;Scale_Factor&quot;,0.9996],PARAMETER[&quot;Latitude_Of_Origin&quot;,0.0],UNIT[&quot;Meter&quot;,1.0],AUTHORITY[&quot;EPSG&quot;,26912]]</WKT><XOrigin>-5120900</XOrigin><YOrigin>-9998100</YOrigin><XYScale>100</XYScale><ZOrigin>0</ZOrigin><ZScale>1</ZScale><MOrigin>0</MOrigin><MScale>1</MScale><XYTolerance>0.10000000000000001</XYTolerance><ZTolerance>0.001</ZTolerance><MTolerance>0.001</MTolerance><HighPrecision>true</HighPrecision><WKID>26912</WKID><LatestWKID>26912</LatestWKID></SpatialReference></Extent><SpatialReference xsi:type='esri:ProjectedCoordinateSystem'><WKT>PROJCS[&quot;NAD_1983_UTM_Zone_12N&quot;,GEOGCS[&quot;GCS_North_American_1983&quot;,DATUM[&quot;D_North_American_1983&quot;,SPHEROID[&quot;GRS_1980&quot;,6378137.0,298.257222101]],PRIMEM[&quot;Greenwich&quot;,0.0],UNIT[&quot;Degree&quot;,0.0174532925199433]],PROJECTION[&quot;Transverse_Mercator&quot;],PARAMETER[&quot;False_Easting&quot;,500000.0],PARAMETER[&quot;False_Northing&quot;,0.0],PARAMETER[&quot;Central_Meridian&quot;,-111.0],PARAMETER[&quot;Scale_Factor&quot;,0.9996],PARAMETER[&quot;Latitude_Of_Origin&quot;,0.0],UNIT[&quot;Meter&quot;,1.0],AUTHORITY[&quot;EPSG&quot;,26912]]</WKT><XOrigin>-5120900</XOrigin><YOrigin>-9998100</YOrigin><XYScale>100</XYScale><ZOrigin>0</ZOrigin><ZScale>1</ZScale><MOrigin>0</MOrigin><MScale>1</MScale><XYTolerance>0.10000000000000001</XYTolerance><ZTolerance>0.001</ZTolerance><MTolerance>0.001</MTolerance><HighPrecision>true</HighPrecision><WKID>26912</WKID><LatestWKID>26912</LatestWKID></SpatialReference><ChangeTracked>false</ChangeTracked></DataElement><DataElement xsi:type='esri:DETable'><CatalogPath>/OC=ProviderServiceAreas</CatalogPath><Name>ProviderServiceAreas</Name><MetadataRetrieved>true</MetadataRetrieved><Metadata xsi:type='esri:XmlPropertySet'><XmlDoc>&lt;metadata xml:lang=&quot;en&quot;&gt;&lt;Esri&gt;&lt;CreaDate&gt;20140618&lt;/CreaDate&gt;&lt;CreaTime&gt;16385200&lt;/CreaTime&gt;&lt;ArcGISFormat&gt;1.0&lt;/ArcGISFormat&gt;&lt;SyncOnce&gt;TRUE&lt;/SyncOnce&gt;&lt;DataProperties&gt;&lt;lineage&gt;&lt;Process ToolSource=&quot;c:\program files\arcgis\desktop10.1\ArcToolbox\Toolboxes\Data Management Tools.tbx\AssignDomainToField&quot; Date=&quot;20140618&quot; Time=&quot;163852&quot;&gt;AssignDomainToField ProviderServiceAreas ServiceClass ServiceClass #&lt;/Process&gt;&lt;Process ToolSource=&quot;c:\program files\arcgis\desktop10.1\ArcToolbox\Toolboxes\Data Management Tools.tbx\Append&quot; Date=&quot;20140623&quot; Time=&quot;152504&quot;&gt;Append ProviderServiceAreas_copy ProviderServiceAreas TEST # #&lt;/Process&gt;&lt;Process ToolSource=&quot;c:\program files (x86)\arcgis\desktop10.2\ArcToolbox\Toolboxes\Data Management Tools.tbx\CalculateField&quot; Date=&quot;20140707&quot; Time=&quot;084211&quot;&gt;CalculateField ProviderServiceAreas ServiceClass &quot;9&quot; VB #&lt;/Process&gt;&lt;/lineage&gt;&lt;/DataProperties&gt;&lt;/Esri&gt;&lt;/metadata&gt;
</XmlDoc></Metadata><DatasetType>esriDTTable</DatasetType><DSID>7</DSID><Versioned>false</Versioned><CanVersion>false</CanVersion><ConfigurationKeyword></ConfigurationKeyword><HasOID>true</HasOID><OIDFieldName>OBJECTID</OIDFieldName><Fields xsi:type='esri:Fields'><FieldArray xsi:type='esri:ArrayOfField'><Field xsi:type='esri:Field'><Name>OBJECTID</Name><Type>esriFieldTypeOID</Type><IsNullable>false</IsNullable><Length>4</Length><Precision>0</Precision><Scale>0</Scale><Required>true</Required><Editable>false</Editable><DomainFixed>true</DomainFixed><AliasName>OBJECTID</AliasName><ModelName>OBJECTID</ModelName></Field><Field xsi:type='esri:Field'><Name>HexID</Name><Type>esriFieldTypeInteger</Type><IsNullable>true</IsNullable><Length>4</Length><Precision>0</Precision><Scale>0</Scale><AliasName>HexID</AliasName><ModelName>HexID</ModelName></Field><Field xsi:type='esri:Field'><Name>ProvName</Name><Type>esriFieldTypeString</Type><IsNullable>true</IsNullable><Length>50</Length><Precision>0</Precision><Scale>0</Scale><AliasName>ProvName</AliasName><ModelName>ProvName</ModelName></Field><Field xsi:type='esri:Field'><Name>ServiceClass</Name><Type>esriFieldTypeSmallInteger</Type><IsNullable>true</IsNullable><Length>2</Length><Precision>0</Precision><Scale>0</Scale><AliasName>ServiceClass</AliasName><ModelName>ServiceClass</ModelName><Domain xsi:type='esri:CodedValueDomain'><DomainName>ServiceClass</DomainName><FieldType>esriFieldTypeSmallInteger</FieldType><MergePolicy>esriMPTDefaultValue</MergePolicy><SplitPolicy>esriSPTDefaultValue</SplitPolicy><Description>ServiceClass</Description><Owner></Owner><CodedValues xsi:type='esri:ArrayOfCodedValue'><CodedValue xsi:type='esri:CodedValue'><Name>Service within 1 month</Name><Code xsi:type='xs:short'>1</Code></CodedValue><CodedValue xsi:type='esri:CodedValue'><Name>Service within 9 months</Name><Code xsi:type='xs:short'>9</Code></CodedValue></CodedValues></Domain></Field></FieldArray></Fields><Indexes xsi:type='esri:Indexes'><IndexArray xsi:type='esri:ArrayOfIndex'><Index xsi:type='esri:Index'><Name>FDO_OBJECTID</Name><IsUnique>true</IsUnique><IsAscending>true</IsAscending><Fields xsi:type='esri:Fields'><FieldArray xsi:type='esri:ArrayOfField'><Field xsi:type='esri:Field'><Name>OBJECTID</Name><Type>esriFieldTypeOID</Type><IsNullable>false</IsNullable><Length>4</Length><Precision>0</Precision><Scale>0</Scale><Required>true</Required><Editable>false</Editable><DomainFixed>true</DomainFixed><AliasName>OBJECTID</AliasName><ModelName>OBJECTID</ModelName></Field></FieldArray></Fields></Index><Index xsi:type='esri:Index'><Name>GDB_7_HexID</Name><IsUnique>false</IsUnique><IsAscending>true</IsAscending><Fields xsi:type='esri:Fields'><FieldArray xsi:type='esri:ArrayOfField'><Field xsi:type='esri:Field'><Name>HexID</Name><Type>esriFieldTypeInteger</Type><IsNullable>true</IsNullable><Length>4</Length><Precision>0</Precision><Scale>0</Scale><AliasName>HexID</AliasName><ModelName>HexID</ModelName></Field></FieldArray></Fields></Index></IndexArray></Indexes><CLSID>{7A566981-C114-11D2-8A28-006097AFF44E}</CLSID><EXTCLSID></EXTCLSID><RelationshipClassNames xsi:type='esri:Names'><Name>HexagontoPSAs</Name></RelationshipClassNames><AliasName>ProviderServiceAreas</AliasName><ModelName></ModelName><HasGlobalID>false</HasGlobalID><GlobalIDFieldName></GlobalIDFieldName><RasterFieldName></RasterFieldName><ExtensionProperties xsi:type='esri:PropertySet'><PropertyArray xsi:type='esri:ArrayOfPropertySetProperty'></PropertyArray></ExtensionProperties><ControllerMemberships xsi:type='esri:ArrayOfControllerMembership'></ControllerMemberships><EditorTrackingEnabled>false</EditorTrackingEnabled><CreatorFieldName></CreatorFieldName><CreatedAtFieldName></CreatedAtFieldName><EditorFieldName></EditorFieldName><EditedAtFieldName></EditedAtFieldName><IsTimeInUTC>true</IsTimeInUTC><ChangeTracked>false</ChangeTracked><FieldFilteringEnabled>false</FieldFilteringEnabled><FilteredFieldNames xsi:type='esri:Names'></FilteredFieldNames></DataElement><DataElement xsi:type='esri:DERelationshipClass'><CatalogPath>/RC=HexagontoPSAs</CatalogPath><Name>HexagontoPSAs</Name><MetadataRetrieved>true</MetadataRetrieved><Metadata xsi:type='esri:XmlPropertySet'><XmlDoc>&lt;?xml version=&quot;1.0&quot;?&gt;
&lt;metadata xml:lang=&quot;en&quot;&gt;&lt;Esri&gt;&lt;CreaDate&gt;20140707&lt;/CreaDate&gt;&lt;CreaTime&gt;08474400&lt;/CreaTime&gt;&lt;ArcGISFormat&gt;1.0&lt;/ArcGISFormat&gt;&lt;SyncOnce&gt;TRUE&lt;/SyncOnce&gt;&lt;/Esri&gt;&lt;/metadata&gt;
</XmlDoc></Metadata><DatasetType>esriDTRelationshipClass</DatasetType><DSID>-1</DSID><Versioned>false</Versioned><CanVersion>false</CanVersion><ConfigurationKeyword></ConfigurationKeyword><HasOID>false</HasOID><OIDFieldName></OIDFieldName><Fields xsi:type='esri:Fields'><FieldArray xsi:type='esri:ArrayOfField'></FieldArray></Fields><Indexes xsi:type='esri:Indexes'><IndexArray xsi:type='esri:ArrayOfIndex'></IndexArray></Indexes><CLSID></CLSID><EXTCLSID></EXTCLSID><RelationshipClassNames xsi:type='esri:Names'></RelationshipClassNames><AliasName></AliasName><ModelName></ModelName><HasGlobalID>false</HasGlobalID><GlobalIDFieldName></GlobalIDFieldName><RasterFieldName></RasterFieldName><ExtensionProperties xsi:type='esri:PropertySet'><PropertyArray xsi:type='esri:ArrayOfPropertySetProperty'></PropertyArray></ExtensionProperties><ControllerMemberships xsi:type='esri:ArrayOfControllerMembership'></ControllerMemberships><EditorTrackingEnabled>false</EditorTrackingEnabled><CreatorFieldName></CreatorFieldName><CreatedAtFieldName></CreatedAtFieldName><EditorFieldName></EditorFieldName><EditedAtFieldName></EditedAtFieldName><IsTimeInUTC>true</IsTimeInUTC><Cardinality>esriRelCardinalityOneToMany</Cardinality><Notification>esriRelNotificationBoth</Notification><IsAttributed>false</IsAttributed><IsComposite>false</IsComposite><OriginClassNames xsi:type='esri:Names'><Name>Hexagons</Name></OriginClassNames><DestinationClassNames xsi:type='esri:Names'><Name>ProviderServiceAreas</Name></DestinationClassNames><KeyType>esriRelKeyTypeSingle</KeyType><ClassKey>esriRelClassKeyUndefined</ClassKey><ForwardPathLabel>ProviderServiceAreas</ForwardPathLabel><BackwardPathLabel>Hexagons</BackwardPathLabel><IsReflexive>false</IsReflexive><OriginClassKeys xsi:type='esri:ArrayOfRelationshipClassKey'><RelationshipClassKey xsi:type='esri:RelationshipClassKey'><ObjectKeyName>HexID</ObjectKeyName><ClassKeyName></ClassKeyName><KeyRole>esriRelKeyRoleOriginPrimary</KeyRole></RelationshipClassKey><RelationshipClassKey xsi:type='esri:RelationshipClassKey'><ObjectKeyName>HexID</ObjectKeyName><ClassKeyName></ClassKeyName><KeyRole>esriRelKeyRoleOriginForeign</KeyRole></RelationshipClassKey></OriginClassKeys><RelationshipRules xsi:type='esri:ArrayOfRelationshipRule'></RelationshipRules><IsAttachmentRelationship>false</IsAttachmentRelationship><ChangeTracked>false</ChangeTracked></DataElement></DatasetDefinitions><Metadata xsi:type='esri:XmlPropertySet'><XmlDoc>&lt;metadata xml:lang=&quot;en&quot;&gt;&lt;Esri&gt;&lt;CreaDate&gt;20140707&lt;/CreaDate&gt;&lt;CreaTime&gt;08365100&lt;/CreaTime&gt;&lt;ArcGISFormat&gt;1.0&lt;/ArcGISFormat&gt;&lt;SyncOnce&gt;TRUE&lt;/SyncOnce&gt;&lt;DataProperties&gt;&lt;lineage&gt;&lt;Process ToolSource=&quot;c:\program files\arcgis\desktop10.1\ArcToolbox\Toolboxes\Data Management Tools.tbx\CreateDomain&quot; Date=&quot;20140617&quot; Time=&quot;163056&quot;&gt;CreateDomain I:\PROJECTS\Broadband\FiberApplication\EconomicDevAppData.gdb AreaCode AreaCode SHORT CODED DEFAULT DEFAULT&lt;/Process&gt;&lt;/lineage&gt;&lt;itemProps&gt;&lt;itemLocation&gt;&lt;linkage Sync=&quot;TRUE&quot;&gt;file://\\AGRC-SDAVISVM03\C$\MapData\EconomicDevAppData.gdb&lt;/linkage&gt;&lt;protocol Sync=&quot;TRUE&quot;&gt;Local Area Network&lt;/protocol&gt;&lt;/itemLocation&gt;&lt;/itemProps&gt;&lt;copyHistory&gt;&lt;copy source=&quot;I:\PROJECTS\Broadband\EconomicDevAppData.gdb&quot; dest=&quot;\\AGRC-SDAVISVM03\C$\MapData\EconomicDevAppData.gdb&quot; date=&quot;20140707&quot; time=&quot;08365100&quot;&gt;&lt;/copy&gt;&lt;/copyHistory&gt;&lt;/DataProperties&gt;&lt;/Esri&gt;&lt;/metadata&gt;
</XmlDoc></Metadata></WorkspaceDefinition><WorkspaceData xsi:type='esri:WorkspaceData'></WorkspaceData></esri:Workspace>